feos/__init__.py
feos/feos.abi3.so
feos-0.9.3.dist-info/METADATA
feos-0.9.3.dist-info/WHEEL
feos-0.9.3.dist-info/RECORD
