Metadata-Version: 2.4
Name: feos
Version: 0.9.3
Requires-Dist: si-units>=0.11.0
Summary: FeOs - A framework for equations of state and classical density functional theory.
Keywords: physics,thermodynamics,equations_of_state,phase_equilibria
Home-Page: https://github.com/feos-org
Author: Gernot Bauer <bauer@itt.uni-stuttgart.de>, Philipp Rehner <prehner@ethz.ch>
Author-email: Gernot Bauer <bauer@itt.uni-stuttgart.de>, Philipp Rehner <prehner@ethz.ch>
License: MIT OR Apache-2.0
Requires-Python: >=3.10
Project-URL: Homepage, https://github.com/feos-org
Project-URL: Source Code, https://github.com/feos-org/feos
